prett/__init__.py
prett/base.py
prett/multi_types.py
prett/project.py
prett/sender.py
prett/setting.py
prett/widget_interface.py
prett6/__init__.py
prett6/base.py
prett6/multi_types.py
prett6/project.py
prett6/sender.py
prett6/setting.py
prett6/widget_interface.py
prett6-1.2.dist-info/LICENSE
prett6-1.2.dist-info/METADATA
prett6-1.2.dist-info/WHEEL
prett6-1.2.dist-info/top_level.txt
prett6-1.2.dist-info/RECORD
