Metadata-Version: 2.1
Name: prett6
Version: 1.2
Summary: A Pretty Project Framework
Home-page: https://github.com/KD-Group/prett
Author: SF-Zhou
Author-email: sfzhou.scut@gmail.com
License: MIT
Keywords: qt ui
Classifier: Development Status :: 3 - Alpha
Classifier: Intended Audience :: Developers
Classifier: License :: OSI Approved :: MIT License
Classifier: Programming Language :: Python :: 3
Classifier: Programming Language :: Python :: 3 :: Only
Classifier: Programming Language :: Python :: 3.8
Classifier: Programming Language :: Python :: 3.9
Classifier: Programming Language :: Python :: 3.10
Requires-Python: >=3.8
License-File: LICENSE
Requires-Dist: PySide6
Requires-Dist: typing
